tracking/__init__.py
tracking/admin.py
tracking/app_settings.py
tracking/apps.py
tracking/base_mixins.py
tracking/base_models.py
tracking/mixins.py
tracking/models.py
tracking/migrations/0001_initial.py
tracking/migrations/__init__.py
tracking/tests/__init__.py
tracking/tests/test_mixins.py
tracking/tests/test_models.py
tracking/tests/urls.py
tracking/tests/views.py
drf_debug-1.2.1.dist-info/METADATA
drf_debug-1.2.1.dist-info/WHEEL
drf_debug-1.2.1.dist-info/top_level.txt
drf_debug-1.2.1.dist-info/RECORD
