Metadata-Version: 2.1
Name: drf-debug
Version: 1.2.1
Summary: API tracking package.
Home-page: https://github.com/dori-dev/drf-debug
Author: Mohammad Dori
Author-email: mr.dori.dev@gmail.com
License: MIT
Classifier: Programming Language :: Python :: 3
Classifier: License :: OSI Approved :: MIT License
Classifier: Operating System :: OS Independent
Requires-Python: >=3.6
Requires-Dist: Django (>=3.2)
Requires-Dist: djangorestframework (>=3.11)
